{
  "parent": "minecraft:recipes/root",
  "criteria": {
    "has_the_recipe": {
      "conditions": {
        "recipe": "bits_n_bobs:tuff_tile_wall"
      },
      "trigger": "minecraft:recipe_unlocked"
    },
    "has_tuff_tiles": {
      "conditions": {
        "items": [
          {
            "items": "bits_n_bobs:tuff_tiles"
          }
        ]
      },
      "trigger": "minecraft:inventory_changed"
    }
  },
  "requirements": [
    [
      "has_the_recipe",
      "has_tuff_tiles"
    ]
  ],
  "rewards": {
    "recipes": [
      "bits_n_bobs:tuff_tile_wall"
    ]
  }
}